LICENSE
README.md
setup.cfg
setup.py
netway/__init__.py
netway/fast.py
netway/get.py
netway/post.py
netway.egg-info/PKG-INFO
netway.egg-info/SOURCES.txt
netway.egg-info/dependency_links.txt
netway.egg-info/requires.txt
netway.egg-info/top_level.txt