Metadata-Version: 2.1
Name: netway
Version: 0.8
Summary: Python internet library
Author: Thesaderror & Mein
Author-email: saderroraz@protonmail.com
Keywords: sockets,request,http,https,get,port,fast
Classifier: Development Status :: 1 - Planning
Classifier: Intended Audience :: Developers
Classifier: Programming Language :: Python :: 3
Classifier: Operating System :: Unix
Classifier: Operating System :: MacOS :: MacOS X
Classifier: Operating System :: Microsoft :: Windows
License-File: LICENSE
